vitejs/__init__.py
vitejs/apps.py
vitejs/templatetags/__init__.py
vitejs/templatetags/vite.py
vitejs/templatetags/__pycache__/__init__.cpython-39.pyc
vitejs/templatetags/__pycache__/vite.cpython-39.pyc
django_vite_simple-1.0.1.dist-info/LICENSE
django_vite_simple-1.0.1.dist-info/METADATA
django_vite_simple-1.0.1.dist-info/WHEEL
django_vite_simple-1.0.1.dist-info/top_level.txt
django_vite_simple-1.0.1.dist-info/RECORD
